README.md
setup.py
client_sdk/__init__.py
client_sdk/api_client.py
client_sdk/configuration.py
client_sdk/exceptions.py
client_sdk/rest.py
client_sdk/api/__init__.py
client_sdk/api/project_api.py
client_sdk/api/version_semantic_api.py
client_sdk/models/__init__.py
client_sdk/models/error.py
client_sdk/models/project.py
client_sdk/models/semver_generate_params.py
client_sdk/models/semver_tag_set.py
reelase_manager_api.egg-info/PKG-INFO
reelase_manager_api.egg-info/SOURCES.txt
reelase_manager_api.egg-info/dependency_links.txt
reelase_manager_api.egg-info/requires.txt
reelase_manager_api.egg-info/top_level.txt
test/test_error.py
test/test_project.py
test/test_project_api.py
test/test_semver_generate_params.py
test/test_semver_tag_set.py
test/test_version_semantic_api.py