Metadata-Version: 1.0
Name: reelase-manager-api
Version: 0.2.0
Summary: Release Manager
Home-page: UNKNOWN
Author: Vital Leshchyk
Author-email: vitalleshchyk@gmail.com
License: 3-Clause BSD
Keywords: OpenAPI,OpenAPI-Generator,Release Manager
Platform: UNKNOWN
